{
  "NIFTY|PUT|-4|2026-05-21 11:15": {
    "verdict": "CAUTION",
    "reason": "Signal score is low (30/100) despite ADX and RSI being acceptable.",
    "risk": "MEDIUM"
  },
  "NIFTY|PUT|-5|2026-05-21 12:25": {
    "verdict": "CAUTION",
    "reason": "Signal score is low (25/100) despite ADX confirming the trend and RSI being within range.",
    "risk": "MEDIUM"
  },
  "NIFTY|PUT|-5|2026-05-21 15:15": {
    "verdict": "CAUTION",
    "reason": "Signal score is low (25/100) despite ADX confirming the trend and RSI being within range.",
    "risk": "MEDIUM"
  },
  "NIFTY|CALL|4|2026-05-22 10:50": {
    "verdict": "CONFIRM",
    "reason": "ADX confirms the trend and RSI is within a reasonable range, supporting the call option buy.",
    "risk": "MEDIUM"
  },
  "NIFTY|CALL|4|2026-05-22 11:20": {
    "verdict": "CONFIRM",
    "reason": "Signal score is good, ADX confirms trend, and VIX is within a manageable range.",
    "risk": "MEDIUM"
  },
  "NIFTY|CALL|5|2026-05-22 11:40": {
    "verdict": "CONFIRM",
    "reason": "Signal score is good, ADX confirms trend, and VIX is within acceptable range for NIFTY.",
    "risk": "MEDIUM"
  },
  "NIFTY|CALL|4|2026-05-22 12:10": {
    "verdict": "CONFIRM",
    "reason": "ADX and RSI support the call direction, and the signal score is acceptable for the DTE.",
    "risk": "MEDIUM"
  },
  "NIFTY|CALL|4|2026-05-22 12:45": {
    "verdict": "CONFIRM",
    "reason": "ADX confirms the trend, RSI is within a reasonable range, and the VIX is within the caution zone but acceptable.",
    "risk": "MEDIUM"
  },
  "NIFTY|CALL|5|2026-05-25 14:40": {
    "verdict": "CONFIRM",
    "reason": "Signal score is high (75/100) and ADX confirms the trend, justifying a buy despite the late time.",
    "risk": "MEDIUM"
  },
  "NIFTY|PUT|-4|2026-05-26 13:00": {
    "verdict": "CAUTION",
    "reason": "Signal score is low (30/100) despite ADX and RSI being favorable, and it's expiry day, requiring a higher score.",
    "risk": "HIGH"
  },
  "NIFTY|PUT|-4|2026-05-26 13:35": {
    "verdict": "CAUTION",
    "reason": "Signal score is low (30/100) despite ADX confirming the trend and RSI being within range.",
    "risk": "MEDIUM"
  },
  "NIFTY|CALL|4|2026-05-27 11:20": {
    "verdict": "CAUTION",
    "reason": "VIX is in the caution zone (14-18), suggesting increased volatility.",
    "risk": "MEDIUM"
  },
  "BANKNIFTY|PUT|-4|2026-05-21 11:15": {
    "verdict": "CAUTION",
    "reason": "Signal score is low and VIX is in the caution zone.",
    "risk": "MEDIUM"
  },
  "BANKNIFTY|PUT|-4|2026-05-21 11:55": {
    "verdict": "CAUTION",
    "reason": "Signal score is low and VIX is in the caution zone.",
    "risk": "MEDIUM"
  },
  "BANKNIFTY|PUT|-4|2026-05-21 12:10": {
    "verdict": "CAUTION",
    "reason": "Signal score is low (30/100) despite ADX confirming the trend and RSI being within range.",
    "risk": "MEDIUM"
  },
  "BANKNIFTY|CALL|5|2026-05-22 10:35": {
    "verdict": "CONFIRM",
    "reason": "ADX confirms the trend and the RSI is within a reasonable range, supporting a call option buy.",
    "risk": "MEDIUM"
  },
  "BANKNIFTY|CALL|5|2026-05-22 10:50": {
    "verdict": "CONFIRM",
    "reason": "ADX confirms the trend and RSI is not overstretched, supporting a call option buy.",
    "risk": "MEDIUM"
  },
  "BANKNIFTY|CALL|5|2026-05-22 11:20": {
    "verdict": "CONFIRM",
    "reason": "ADX and RSI support the call direction, and VIX is within a manageable range.",
    "risk": "MEDIUM"
  },
  "BANKNIFTY|CALL|5|2026-05-22 11:40": {
    "verdict": "CONFIRM",
    "reason": "ADX confirms the trend and RSI is within a reasonable range, supporting the call option.",
    "risk": "MEDIUM"
  },
  "BANKNIFTY|CALL|5|2026-05-22 12:25": {
    "verdict": "CONFIRM",
    "reason": "ADX confirms the trend, RSI is not overbought, and the VIX is within a manageable range.",
    "risk": "MEDIUM"
  },
  "BANKNIFTY|CALL|5|2026-05-22 12:40": {
    "verdict": "CAUTION",
    "reason": "VIX is in the caution zone (14-18), requiring careful monitoring.",
    "risk": "MEDIUM"
  },
  "BANKNIFTY|CALL|5|2026-05-22 15:20": {
    "verdict": "CAUTION",
    "reason": "Late entry at 3:20 PM increases risk due to theta decay, despite acceptable ADX and RSI.",
    "risk": "MEDIUM"
  },
  "BANKNIFTY|CALL|4|2026-05-25 10:55": {
    "verdict": "CAUTION",
    "reason": "DTE is 1, requiring a higher signal score, and VIX is in the caution zone.",
    "risk": "MEDIUM"
  },
  "BANKNIFTY|CALL|5|2026-05-25 12:15": {
    "verdict": "CONFIRM",
    "reason": "ADX confirms the trend and the signal score is high enough to trade on expiry day.",
    "risk": "MEDIUM"
  },
  "BANKNIFTY|CALL|4|2026-05-25 14:30": {
    "verdict": "CAUTION",
    "reason": "Time is valid but close to market close, increasing theta decay risk.",
    "risk": "MEDIUM"
  },
  "BANKNIFTY|PUT|-4|2026-05-26 12:10": {
    "verdict": "CAUTION",
    "reason": "Signal score is low (30/100) despite ADX and RSI being favorable, and VIX is in the caution zone.",
    "risk": "MEDIUM"
  },
  "BANKNIFTY|PUT|-4|2026-05-26 12:25": {
    "verdict": "CAUTION",
    "reason": "VIX is in the caution zone (14-18) and the signal score is low.",
    "risk": "MEDIUM"
  },
  "BANKNIFTY|PUT|-5|2026-05-26 12:40": {
    "verdict": "CAUTION",
    "reason": "RBI's USD/INR swap auction introduces significant volatility risk, especially given the already low signal score.",
    "risk": "HIGH"
  },
  "BANKNIFTY|PUT|-4|2026-05-27 13:05": {
    "verdict": "CAUTION",
    "reason": "Signal score is low and VIX is in the caution zone, indicating increased volatility.",
    "risk": "MEDIUM"
  },
  "BANKNIFTY|PUT|-4|2026-05-27 13:15": {
    "verdict": "CAUTION",
    "reason": "Signal score is low (30/100) despite ADX and RSI being favorable, suggesting a weak conviction trade.",
    "risk": "MEDIUM"
  },
  "BANKNIFTY|PUT|-4|2026-05-27 13:25": {
    "verdict": "CAUTION",
    "reason": "Signal score is low (30/100) despite ADX and RSI being favorable, suggesting weak conviction.",
    "risk": "MEDIUM"
  },
  "BANKNIFTY|PUT|-4|2026-05-27 13:40": {
    "verdict": "CAUTION",
    "reason": "Signal score is low (30/100) despite ADX and RSI being favorable, and geopolitical uncertainty adds risk.",
    "risk": "MEDIUM"
  },
  "BANKNIFTY|PUT|-4|2026-05-27 14:35": {
    "verdict": "CAUTION",
    "reason": "Signal score is low and VIX is in the caution zone, despite ADX confirming the trend.",
    "risk": "MEDIUM"
  },
  "SENSEX|PUT|-4|2026-05-21 11:10": {
    "verdict": "CAUTION",
    "reason": "Signal score is low (30/100) despite ADX confirming the trend and RSI being within range.",
    "risk": "MEDIUM"
  },
  "SENSEX|PUT|-4|2026-05-21 12:20": {
    "verdict": "CAUTION",
    "reason": "Signal score is low (30/100) despite ADX confirming trend and RSI being within range.",
    "risk": "MEDIUM"
  },
  "SENSEX|PUT|-5|2026-05-21 15:25": {
    "verdict": "SKIP",
    "reason": "Signal Score is too low (25/100) for expiry day trading.",
    "risk": "HIGH"
  },
  "SENSEX|CALL|4|2026-05-22 10:55": {
    "verdict": "CAUTION",
    "reason": "VIX is at a cautionary level of 15.0, increasing risk.",
    "risk": "MEDIUM"
  },
  "SENSEX|CALL|4|2026-05-22 11:20": {
    "verdict": "CONFIRM",
    "reason": "ADX confirms the trend and the RSI is within a reasonable range, supporting the call option direction.",
    "risk": "MEDIUM"
  },
  "SENSEX|CALL|5|2026-05-22 11:40": {
    "verdict": "CONFIRM",
    "reason": "ADX confirms the trend and RSI is within a reasonable range, supporting the call option buy.",
    "risk": "MEDIUM"
  },
  "SENSEX|CALL|4|2026-05-22 12:10": {
    "verdict": "CONFIRM",
    "reason": "ADX confirms the trend and RSI is within a reasonable range, supporting the call option buy.",
    "risk": "MEDIUM"
  },
  "SENSEX|CALL|4|2026-05-22 12:40": {
    "verdict": "CONFIRM",
    "reason": "ADX confirms the trend and the signal score is acceptable for the DTE.",
    "risk": "MEDIUM"
  },
  "SENSEX|CALL|4|2026-05-25 11:35": {
    "verdict": "CONFIRM",
    "reason": "ADX confirms the trend and RSI is within a reasonable range, supporting the call option buy.",
    "risk": "MEDIUM"
  },
  "SENSEX|CALL|4|2026-05-25 13:25": {
    "verdict": "CONFIRM",
    "reason": "ADX confirms the trend, RSI is not overbought, and the VIX is within a manageable range, aligning with positive market sentiment.",
    "risk": "MEDIUM"
  },
  "SENSEX|CALL|4|2026-05-25 14:35": {
    "verdict": "CONFIRM",
    "reason": "ADX confirms the trend and the RSI is not overbought, supporting a call option buy.",
    "risk": "MEDIUM"
  },
  "SENSEX|PUT|-4|2026-05-26 12:40": {
    "verdict": "CAUTION",
    "reason": "Signal score is low (30/100) despite ADX confirming the trend and RSI being within range.",
    "risk": "MEDIUM"
  },
  "SENSEX|PUT|-4|2026-05-26 13:00": {
    "verdict": "CAUTION",
    "reason": "The signal score is low (30/100), indicating a weak setup despite ADX confirmation and RSI alignment.",
    "risk": "MEDIUM"
  },
  "SENSEX|PUT|-4|2026-05-26 13:35": {
    "verdict": "CAUTION",
    "reason": "The signal score is low (30/100), indicating a weak setup despite ADX confirming the trend and RSI not being overbought.",
    "risk": "MEDIUM"
  },
  "SENSEX|CALL|4|2026-05-27 11:20": {
    "verdict": "CAUTION",
    "reason": "DTE is 1, requiring a higher signal score than the current 70.",
    "risk": "HIGH"
  }
}